Metadata-Version: 2.4
Name: pipecat-ai
Version: 0.0.101
Summary: An open source framework for voice (and multimodal) assistants
License-Expression: BSD-2-Clause
Project-URL: Homepage, https://pipecat.ai
Project-URL: Documentation, https://docs.pipecat.ai/
Project-URL: Source, https://github.com/pipecat-ai/pipecat
Project-URL: Issues, https://github.com/pipecat-ai/pipecat/issues
Project-URL: Changelog, https://github.com/pipecat-ai/pipecat/blob/main/CHANGELOG.md
Keywords: webrtc,audio,video,ai
Classifier: Development Status :: 5 - Production/Stable
Classifier: Intended Audience :: Developers
Classifier: Topic :: Communications :: Conferencing
Classifier: Topic :: Multimedia :: Sound/Audio
Classifier: Topic :: Multimedia :: Video
Classifier: Topic :: Scientific/Engineering :: Artificial Intelligence
Requires-Python: >=3.10
License-File: LICENSE
Requires-Dist: aiofiles<25,>=24.1.0
Requires-Dist: aiohttp<4,>=3.11.12
Requires-Dist: audioop-lts~=0.2.1; python_version >= "3.13"
Requires-Dist: docstring_parser~=0.16
Requires-Dist: loguru~=0.7.3
Requires-Dist: Markdown<4,>=3.7
Requires-Dist: nltk<4,>=3.9.1
Requires-Dist: numpy<3,>=1.26.4
Requires-Dist: Pillow<12,>=11.1.0
Requires-Dist: protobuf~=5.29.3
Requires-Dist: pydantic<3,>=2.10.6
Requires-Dist: pyloudnorm~=0.1.1
Requires-Dist: resampy~=0.4.3
Requires-Dist: soxr~=0.5.0
Requires-Dist: openai<3,>=1.74.0
Requires-Dist: numba==0.61.2
Requires-Dist: wait_for2>=0.4.1; python_version < "3.12"
Provides-Extra: aic
Requires-Dist: aic-sdk~=2.0.1; extra == "aic"
Provides-Extra: anthropic
Requires-Dist: anthropic~=0.49.0; extra == "anthropic"
Provides-Extra: assemblyai
Requires-Dist: pipecat-ai[websockets-base]; extra == "assemblyai"
Provides-Extra: asyncai
Requires-Dist: pipecat-ai[websockets-base]; extra == "asyncai"
Provides-Extra: aws
Requires-Dist: aioboto3~=15.5.0; extra == "aws"
Requires-Dist: pipecat-ai[websockets-base]; extra == "aws"
Provides-Extra: aws-nova-sonic
Requires-Dist: aws_sdk_bedrock_runtime~=0.2.0; python_version >= "3.12" and extra == "aws-nova-sonic"
Provides-Extra: azure
Requires-Dist: azure-cognitiveservices-speech~=1.47.0; extra == "azure"
Provides-Extra: cartesia
Requires-Dist: cartesia~=2.0.3; extra == "cartesia"
Requires-Dist: pipecat-ai[websockets-base]; extra == "cartesia"
Provides-Extra: camb
Requires-Dist: camb-sdk>=1.5.4; extra == "camb"
Provides-Extra: cerebras
Provides-Extra: daily
Requires-Dist: daily-python~=0.23.0; extra == "daily"
Provides-Extra: deepgram
Requires-Dist: deepgram-sdk~=4.7.0; extra == "deepgram"
Requires-Dist: pipecat-ai[websockets-base]; extra == "deepgram"
Provides-Extra: deepseek
Provides-Extra: elevenlabs
Requires-Dist: pipecat-ai[websockets-base]; extra == "elevenlabs"
Provides-Extra: fal
Requires-Dist: fal-client~=0.5.9; extra == "fal"
Provides-Extra: fireworks
Provides-Extra: fish
Requires-Dist: ormsgpack~=1.7.0; extra == "fish"
Requires-Dist: pipecat-ai[websockets-base]; extra == "fish"
Provides-Extra: gladia
Requires-Dist: pipecat-ai[websockets-base]; extra == "gladia"
Provides-Extra: google
Requires-Dist: google-cloud-speech<3,>=2.33.0; extra == "google"
Requires-Dist: google-cloud-texttospeech<3,>=2.31.0; extra == "google"
Requires-Dist: google-genai<2,>=1.57.0; extra == "google"
Requires-Dist: pipecat-ai[websockets-base]; extra == "google"
Provides-Extra: gradium
Requires-Dist: pipecat-ai[websockets-base]; extra == "gradium"
Provides-Extra: grok
Provides-Extra: groq
Requires-Dist: groq~=0.23.0; extra == "groq"
Provides-Extra: gstreamer
Requires-Dist: pygobject~=3.50.0; extra == "gstreamer"
Provides-Extra: heygen
Requires-Dist: livekit>=1.0.13; extra == "heygen"
Requires-Dist: pipecat-ai[websockets-base]; extra == "heygen"
Provides-Extra: hume
Requires-Dist: hume>=0.11.2; extra == "hume"
Provides-Extra: inworld
Provides-Extra: koala
Requires-Dist: pvkoala~=2.0.3; extra == "koala"
Provides-Extra: kokoro
Requires-Dist: kokoro<1,>=0.9.4; extra == "kokoro"
Requires-Dist: requests<3,>=2.32.5; extra == "kokoro"
Provides-Extra: krisp
Requires-Dist: pipecat-ai-krisp~=0.4.0; extra == "krisp"
Provides-Extra: langchain
Requires-Dist: langchain~=0.3.20; extra == "langchain"
Requires-Dist: langchain-community~=0.3.20; extra == "langchain"
Requires-Dist: langchain-openai~=0.3.9; extra == "langchain"
Provides-Extra: livekit
Requires-Dist: livekit~=1.0.13; extra == "livekit"
Requires-Dist: livekit-api~=1.0.5; extra == "livekit"
Requires-Dist: tenacity<10.0.0,>=8.2.3; extra == "livekit"
Requires-Dist: pyjwt>=2.10.1; extra == "livekit"
Provides-Extra: lmnt
Requires-Dist: pipecat-ai[websockets-base]; extra == "lmnt"
Provides-Extra: local
Requires-Dist: pyaudio~=0.2.14; extra == "local"
Provides-Extra: local-smart-turn
Requires-Dist: coremltools>=8.0; extra == "local-smart-turn"
Requires-Dist: transformers; extra == "local-smart-turn"
Requires-Dist: torch<3,>=2.5.0; extra == "local-smart-turn"
Requires-Dist: torchaudio<3,>=2.5.0; extra == "local-smart-turn"
Provides-Extra: local-smart-turn-v3
Requires-Dist: transformers; extra == "local-smart-turn-v3"
Requires-Dist: onnxruntime<2,>=1.20.1; extra == "local-smart-turn-v3"
Provides-Extra: mcp
Requires-Dist: mcp[cli]<2,>=1.11.0; extra == "mcp"
Provides-Extra: mem0
Requires-Dist: mem0ai~=0.1.94; extra == "mem0"
Provides-Extra: mistral
Provides-Extra: mlx-whisper
Requires-Dist: mlx-whisper~=0.4.2; extra == "mlx-whisper"
Provides-Extra: moondream
Requires-Dist: accelerate~=1.10.0; extra == "moondream"
Requires-Dist: einops~=0.8.0; extra == "moondream"
Requires-Dist: pyvips[binary]~=3.0.0; extra == "moondream"
Requires-Dist: timm~=1.0.13; extra == "moondream"
Requires-Dist: transformers>=4.48.0; extra == "moondream"
Provides-Extra: neuphonic
Requires-Dist: pipecat-ai[websockets-base]; extra == "neuphonic"
Provides-Extra: noisereduce
Requires-Dist: noisereduce~=3.0.3; extra == "noisereduce"
Provides-Extra: nvidia
Requires-Dist: nvidia-riva-client~=2.21.1; extra == "nvidia"
Provides-Extra: openai
Requires-Dist: pipecat-ai[websockets-base]; extra == "openai"
Provides-Extra: rnnoise
Requires-Dist: pyrnnoise~=0.4.1; extra == "rnnoise"
Provides-Extra: openpipe
Requires-Dist: openpipe<6,>=4.50.0; extra == "openpipe"
Provides-Extra: openrouter
Provides-Extra: perplexity
Provides-Extra: piper
Requires-Dist: piper-tts<2,>=1.3.0; extra == "piper"
Requires-Dist: requests<3,>=2.32.5; extra == "piper"
Provides-Extra: playht
Requires-Dist: pipecat-ai[websockets-base]; extra == "playht"
Provides-Extra: qwen
Provides-Extra: remote-smart-turn
Provides-Extra: rime
Requires-Dist: pipecat-ai[websockets-base]; extra == "rime"
Provides-Extra: riva
Requires-Dist: pipecat-ai[nvidia]; extra == "riva"
Provides-Extra: runner
Requires-Dist: python-dotenv<2.0.0,>=1.0.0; extra == "runner"
Requires-Dist: uvicorn<1.0.0,>=0.32.0; extra == "runner"
Requires-Dist: fastapi<0.128.0,>=0.115.6; extra == "runner"
Requires-Dist: pipecat-ai-small-webrtc-prebuilt>=2.0.4; extra == "runner"
Provides-Extra: sagemaker
Requires-Dist: aws_sdk_sagemaker_runtime_http2; python_version >= "3.12" and extra == "sagemaker"
Provides-Extra: sambanova
Provides-Extra: sarvam
Requires-Dist: sarvamai==0.1.21; extra == "sarvam"
Requires-Dist: pipecat-ai[websockets-base]; extra == "sarvam"
Provides-Extra: sentry
Requires-Dist: sentry-sdk<3,>=2.28.0; extra == "sentry"
Provides-Extra: silero
Requires-Dist: onnxruntime<2,>=1.20.1; extra == "silero"
Provides-Extra: simli
Requires-Dist: simli-ai~=1.0.3; extra == "simli"
Provides-Extra: soniox
Requires-Dist: pipecat-ai[websockets-base]; extra == "soniox"
Provides-Extra: soundfile
Requires-Dist: soundfile~=0.13.1; extra == "soundfile"
Provides-Extra: speechmatics
Requires-Dist: speechmatics-voice[smart]>=0.2.8; extra == "speechmatics"
Provides-Extra: strands
Requires-Dist: strands-agents<2,>=1.9.1; extra == "strands"
Provides-Extra: tavus
Provides-Extra: together
Provides-Extra: tracing
Requires-Dist: opentelemetry-sdk>=1.33.0; extra == "tracing"
Requires-Dist: opentelemetry-api>=1.33.0; extra == "tracing"
Requires-Dist: opentelemetry-instrumentation>=0.54b0; extra == "tracing"
Provides-Extra: ultravox
Requires-Dist: pipecat-ai[websockets-base]; extra == "ultravox"
Provides-Extra: webrtc
Requires-Dist: aiortc<2,>=1.14.0; extra == "webrtc"
Requires-Dist: opencv-python<5,>=4.11.0.86; extra == "webrtc"
Provides-Extra: websocket
Requires-Dist: pipecat-ai[websockets-base]; extra == "websocket"
Requires-Dist: fastapi<0.128.0,>=0.115.6; extra == "websocket"
Provides-Extra: websockets-base
Requires-Dist: websockets<16.0,>=13.1; extra == "websockets-base"
Provides-Extra: whisper
Requires-Dist: faster-whisper~=1.1.1; extra == "whisper"
Dynamic: license-file
